{
  "updated": 2,
  "timestamp": "2026-02-04T05:18:32.509Z",
  "lists": [
    {
      "filename": "easylist.txt",
      "url": "https://easylist.to/easylist/easylist.txt",
      "hash": "49b14b32a33753750045be52d1fda60e07888e21503498629ef22ed3892cbad4",
      "version": "202602040506",
      "lastModified": "2026-02-04T05:06:39.000Z",
      "contentLastModified": "04 Feb 2026 05:06 UTC",
      "serverLastModified": "Wed, 04 Feb 2026 05:06:39 GMT",
      "etag": "W/\"6982d3df-20a3c7\"",
      "size": 2138533,
      "changeReason": "content hash changed and timestamp newer and ETag changed",
      "expires": "4 days (update frequency)",
      "ageHours": "0.2",
      "isStale": false,
      "ageAnalysis": "Fresh: 0.2 hours old"
    },
    {
      "filename": "easyprivacy.txt",
      "url": "https://easylist.to/easylist/easyprivacy.txt",
      "hash": "f0d42fdfaa791a3966b34f306404c6731651a7e76b5b0de0db2ae3c33de8b762",
      "version": "202602040506",
      "lastModified": "2026-02-04T05:06:39.000Z",
      "contentLastModified": "04 Feb 2026 05:06 UTC",
      "serverLastModified": "Wed, 04 Feb 2026 05:06:39 GMT",
      "etag": "W/\"6982d3df-166b07\"",
      "size": 1469191,
      "changeReason": "content hash changed and timestamp newer and ETag changed",
      "expires": "4 days (update frequency)",
      "ageHours": "0.2",
      "isStale": false,
      "ageAnalysis": "Fresh: 0.2 hours old"
    }
  ],
  "staleFiles": []
}