{
  "updated": 2,
  "timestamp": "2026-06-07T19:28:46.051Z",
  "lists": [
    {
      "filename": "easylist.txt",
      "url": "https://easylist.to/easylist/easylist.txt",
      "hash": "cc6f66582f67438414db3df4dfb026b193767db04274e835eead9d9e46e385c8",
      "version": "202606071910",
      "lastModified": "2026-06-07T19:10:55.000Z",
      "contentLastModified": "07 Jun 2026 19:10 UTC",
      "serverLastModified": "Sun, 07 Jun 2026 19:10:55 GMT",
      "etag": "W/\"6a25c23f-221715\"",
      "size": 2233215,
      "changeReason": "content hash changed and timestamp newer and ETag changed",
      "expires": "4 days (update frequency)",
      "ageHours": "0.3",
      "isStale": false,
      "ageAnalysis": "Fresh: 0.3 hours old"
    },
    {
      "filename": "easyprivacy.txt",
      "url": "https://easylist.to/easylist/easyprivacy.txt",
      "hash": "2308c1e1e519ae465c21bdaf9d6b3f5f5db7569e86925513acd70d45c4259092",
      "version": "202606071922",
      "lastModified": "2026-06-07T19:22:58.000Z",
      "contentLastModified": "07 Jun 2026 19:22 UTC",
      "serverLastModified": "Sun, 07 Jun 2026 19:22:58 GMT",
      "etag": "W/\"6a25c512-16a5bb\"",
      "size": 1484219,
      "changeReason": "content hash changed and timestamp newer and ETag changed",
      "expires": "4 days (update frequency)",
      "ageHours": "0.1",
      "isStale": false,
      "ageAnalysis": "Fresh: 0.1 hours old"
    }
  ],
  "staleFiles": []
}