{
  "updated": 2,
  "timestamp": "2025-12-10T10:01:45.936Z",
  "lists": [
    {
      "filename": "easylist.txt",
      "url": "https://easylist.to/easylist/easylist.txt",
      "hash": "24fec52a7a0b295183ce89d783a33fac50eea206f13cb6b5711112ff664fcd21",
      "version": "202512100944",
      "lastModified": "2025-12-10T09:45:29.000Z",
      "contentLastModified": "10 Dec 2025 09:44 UTC",
      "serverLastModified": "Wed, 10 Dec 2025 09:45:29 GMT",
      "etag": "W/\"69394139-1e0cb7\"",
      "size": 1968789,
      "changeReason": "content hash changed and timestamp newer and ETag changed",
      "expires": "4 days (update frequency)",
      "ageHours": "0.3",
      "isStale": false,
      "ageAnalysis": "Fresh: 0.3 hours old"
    },
    {
      "filename": "easyprivacy.txt",
      "url": "https://easylist.to/easylist/easyprivacy.txt",
      "hash": "6211f7f35f3a04ab94859692bd65775e682d9cb1aa8d387c90003fbdbad1a853",
      "version": "202512100944",
      "lastModified": "2025-12-10T09:45:29.000Z",
      "contentLastModified": "10 Dec 2025 09:44 UTC",
      "serverLastModified": "Wed, 10 Dec 2025 09:45:29 GMT",
      "etag": "W/\"69394139-1642c9\"",
      "size": 1458889,
      "changeReason": "content hash changed and timestamp newer and ETag changed",
      "expires": "4 days (update frequency)",
      "ageHours": "0.3",
      "isStale": false,
      "ageAnalysis": "Fresh: 0.3 hours old"
    }
  ],
  "staleFiles": []
}