{
  "updated": 2,
  "timestamp": "2026-06-12T07:29:58.821Z",
  "lists": [
    {
      "filename": "easylist.txt",
      "url": "https://easylist.to/easylist/easylist.txt",
      "hash": "b33bf5a7f6e0c41576bdf1bc0f15c1c0947f4b477bad3dcce6eb6b0d3f04301c",
      "version": "202606120716",
      "lastModified": "2026-06-12T07:17:49.000Z",
      "contentLastModified": "12 Jun 2026 07:16 UTC",
      "serverLastModified": "Fri, 12 Jun 2026 07:17:49 GMT",
      "etag": "W/\"6a2bb29d-20acc0\"",
      "size": 2140458,
      "changeReason": "content hash changed and timestamp newer and ETag changed",
      "expires": "4 days (update frequency)",
      "ageHours": "0.2",
      "isStale": false,
      "ageAnalysis": "Fresh: 0.2 hours old"
    },
    {
      "filename": "easyprivacy.txt",
      "url": "https://easylist.to/easylist/easyprivacy.txt",
      "hash": "ac5ff655944bdb80d4a0df8a0e9a6757ebf158180b8993ba4b266ea85de420e5",
      "version": "202606120725",
      "lastModified": "2026-06-12T07:26:14.000Z",
      "contentLastModified": "12 Jun 2026 07:25 UTC",
      "serverLastModified": "Fri, 12 Jun 2026 07:26:14 GMT",
      "etag": "W/\"6a2bb496-16a834\"",
      "size": 1484852,
      "changeReason": "content hash changed and timestamp newer and ETag changed",
      "expires": "4 days (update frequency)",
      "ageHours": "0.1",
      "isStale": false,
      "ageAnalysis": "Fresh: 0.1 hours old"
    }
  ],
  "staleFiles": []
}