{
  "updated": 1,
  "timestamp": "2026-01-29T22:03:09.923Z",
  "lists": [
    {
      "filename": "easylist.txt",
      "url": "https://easylist.to/easylist/easylist.txt",
      "hash": "4330c07b324a984637b04af9b505c204cc14768d78c29864919bc3b7ca556e6a",
      "version": "202601292153",
      "lastModified": "2026-01-29T21:53:59.000Z",
      "contentLastModified": "29 Jan 2026 21:53 UTC",
      "serverLastModified": "Thu, 29 Jan 2026 21:53:59 GMT",
      "etag": "W/\"697bd6f7-2113d6\"",
      "size": 2167220,
      "changeReason": "content hash changed and timestamp newer and ETag changed",
      "expires": "4 days (update frequency)",
      "ageHours": "0.2",
      "isStale": false,
      "ageAnalysis": "Fresh: 0.2 hours old"
    }
  ],
  "staleFiles": []
}