{
  "updated": 2,
  "timestamp": "2026-02-04T11:10:25.236Z",
  "lists": [
    {
      "filename": "easylist.txt",
      "url": "https://easylist.to/easylist/easylist.txt",
      "hash": "69ec456ad594e0d47c44add130429f2a9201d617058e8bd913f83db1a1c2531e",
      "version": "202602041106",
      "lastModified": "2026-02-04T11:07:12.000Z",
      "contentLastModified": "04 Feb 2026 11:06 UTC",
      "serverLastModified": "Wed, 04 Feb 2026 11:07:12 GMT",
      "etag": "W/\"69832860-20ab59\"",
      "size": 2140471,
      "changeReason": "content hash changed and timestamp newer and ETag changed",
      "expires": "4 days (update frequency)",
      "ageHours": "0.1",
      "isStale": false,
      "ageAnalysis": "Fresh: 0.1 hours old"
    },
    {
      "filename": "easyprivacy.txt",
      "url": "https://easylist.to/easylist/easyprivacy.txt",
      "hash": "f66f1da23572c249b2d318d492bcf2bc98a7496609612c4808d860b12b7d7e96",
      "version": "202602041059",
      "lastModified": "2026-02-04T11:00:25.000Z",
      "contentLastModified": "04 Feb 2026 10:59 UTC",
      "serverLastModified": "Wed, 04 Feb 2026 11:00:25 GMT",
      "etag": "W/\"698326c9-166baf\"",
      "size": 1469359,
      "changeReason": "content hash changed and timestamp newer and ETag changed",
      "expires": "4 days (update frequency)",
      "ageHours": "0.2",
      "isStale": false,
      "ageAnalysis": "Fresh: 0.2 hours old"
    }
  ],
  "staleFiles": []
}