{
  "updated": 2,
  "timestamp": "2026-02-07T05:15:44.256Z",
  "lists": [
    {
      "filename": "easylist.txt",
      "url": "https://easylist.to/easylist/easylist.txt",
      "hash": "b5193ecd964720b19f3ce54d3432cb708cc3c5160c1691c95eaedad45c2c2928",
      "version": "202602070504",
      "lastModified": "2026-02-07T05:04:43.000Z",
      "contentLastModified": "07 Feb 2026 05:04 UTC",
      "serverLastModified": "Sat, 07 Feb 2026 05:04:43 GMT",
      "etag": "W/\"6986c7eb-20e357\"",
      "size": 2154805,
      "changeReason": "content hash changed and timestamp newer and ETag changed",
      "expires": "4 days (update frequency)",
      "ageHours": "0.2",
      "isStale": false,
      "ageAnalysis": "Fresh: 0.2 hours old"
    },
    {
      "filename": "easyprivacy.txt",
      "url": "https://easylist.to/easylist/easyprivacy.txt",
      "hash": "2b3f115d5ad9b3e6d8fab8df8b703b1576c661e37d659b3332753e49c22ec5bf",
      "version": "202602070504",
      "lastModified": "2026-02-07T05:04:43.000Z",
      "contentLastModified": "07 Feb 2026 05:04 UTC",
      "serverLastModified": "Sat, 07 Feb 2026 05:04:43 GMT",
      "etag": "W/\"6986c7eb-166d38\"",
      "size": 1469752,
      "changeReason": "content hash changed and timestamp newer and ETag changed",
      "expires": "4 days (update frequency)",
      "ageHours": "0.2",
      "isStale": false,
      "ageAnalysis": "Fresh: 0.2 hours old"
    }
  ],
  "staleFiles": []
}