{
  "updated": 2,
  "timestamp": "2025-12-14T16:01:26.644Z",
  "lists": [
    {
      "filename": "easylist.txt",
      "url": "https://easylist.to/easylist/easylist.txt",
      "hash": "7c62a33cda8cf762300aa24291cc5b5bab756bdb39b2a3f28dbb71edc0737907",
      "version": "202512141551",
      "lastModified": "2025-12-14T15:51:42.000Z",
      "contentLastModified": "14 Dec 2025 15:51 UTC",
      "serverLastModified": "Sun, 14 Dec 2025 15:51:42 GMT",
      "etag": "W/\"693edd0e-1e7200\"",
      "size": 1994718,
      "changeReason": "content hash changed and timestamp newer and ETag changed",
      "expires": "4 days (update frequency)",
      "ageHours": "0.2",
      "isStale": false,
      "ageAnalysis": "Fresh: 0.2 hours old"
    },
    {
      "filename": "easyprivacy.txt",
      "url": "https://easylist.to/easylist/easyprivacy.txt",
      "hash": "70fea9af2917a0356cd70f71915bb19ef5d13a7ebb58495dde4911e104161b3c",
      "version": "202512141551",
      "lastModified": "2025-12-14T15:51:42.000Z",
      "contentLastModified": "14 Dec 2025 15:51 UTC",
      "serverLastModified": "Sun, 14 Dec 2025 15:51:42 GMT",
      "etag": "W/\"693edd0e-1646e1\"",
      "size": 1459937,
      "changeReason": "content hash changed and timestamp newer and ETag changed",
      "expires": "4 days (update frequency)",
      "ageHours": "0.2",
      "isStale": false,
      "ageAnalysis": "Fresh: 0.2 hours old"
    }
  ],
  "staleFiles": []
}