{
  "updated": 2,
  "timestamp": "2026-02-06T03:45:41.258Z",
  "lists": [
    {
      "filename": "easylist.txt",
      "url": "https://easylist.to/easylist/easylist.txt",
      "hash": "2e29c343edb703fb810470a590cd0f6de7b1d6d6833d1fb9ac9d20319ce8ed3c",
      "version": "202602060327",
      "lastModified": "2026-02-06T03:27:48.000Z",
      "contentLastModified": "06 Feb 2026 03:27 UTC",
      "serverLastModified": "Fri, 06 Feb 2026 03:27:48 GMT",
      "etag": "W/\"69855fb4-20ce8e\"",
      "size": 2149484,
      "changeReason": "content hash changed and timestamp newer and ETag changed",
      "expires": "4 days (update frequency)",
      "ageHours": "0.3",
      "isStale": false,
      "ageAnalysis": "Fresh: 0.3 hours old"
    },
    {
      "filename": "easyprivacy.txt",
      "url": "https://easylist.to/easylist/easyprivacy.txt",
      "hash": "487e4c4bd851dc24aa793b52d35530f0bb5266d5429683b308735d4d8a42f148",
      "version": "202602060327",
      "lastModified": "2026-02-06T03:27:48.000Z",
      "contentLastModified": "06 Feb 2026 03:27 UTC",
      "serverLastModified": "Fri, 06 Feb 2026 03:27:48 GMT",
      "etag": "W/\"69855fb4-166c03\"",
      "size": 1469443,
      "changeReason": "content hash changed and timestamp newer and ETag changed",
      "expires": "4 days (update frequency)",
      "ageHours": "0.3",
      "isStale": false,
      "ageAnalysis": "Fresh: 0.3 hours old"
    }
  ],
  "staleFiles": []
}