{
  "updated": 1,
  "timestamp": "2026-01-28T07:05:42.566Z",
  "lists": [
    {
      "filename": "easyprivacy.txt",
      "url": "https://easylist.to/easylist/easyprivacy.txt",
      "hash": "15b903efbda44e480e5061d520f6adea512fe3f5662bc21497b55d661f2f1344",
      "version": "202601280657",
      "lastModified": "2026-01-28T06:57:45.000Z",
      "contentLastModified": "28 Jan 2026 06:57 UTC",
      "serverLastModified": "Wed, 28 Jan 2026 06:57:45 GMT",
      "etag": "W/\"6979b369-16666f\"",
      "size": 1468015,
      "changeReason": "content hash changed and timestamp newer and ETag changed",
      "expires": "4 days (update frequency)",
      "ageHours": "0.1",
      "isStale": false,
      "ageAnalysis": "Fresh: 0.1 hours old"
    }
  ],
  "staleFiles": []
}