{
  "updated": 2,
  "timestamp": "2025-12-31T18:01:45.509Z",
  "lists": [
    {
      "filename": "easylist.txt",
      "url": "https://easylist.to/easylist/easylist.txt",
      "hash": "152d73e024df2db81b88c79dd47aa1d6e42bfc3e5c6847e9ec6ecbd76d71679b",
      "version": "202512311750",
      "lastModified": "2025-12-31T17:50:53.000Z",
      "contentLastModified": "31 Dec 2025 17:50 UTC",
      "serverLastModified": "Wed, 31 Dec 2025 17:50:53 GMT",
      "etag": "W/\"6955627d-202b60\"",
      "size": 2107710,
      "changeReason": "content hash changed and timestamp newer and ETag changed",
      "expires": "4 days (update frequency)",
      "ageHours": "0.2",
      "isStale": false,
      "ageAnalysis": "Fresh: 0.2 hours old"
    },
    {
      "filename": "easyprivacy.txt",
      "url": "https://easylist.to/easylist/easyprivacy.txt",
      "hash": "e19635b0b3c6886b83debfaca81b2e8c04aa0270615d07c6ee670f41e0e7c2b2",
      "version": "202512311750",
      "lastModified": "2025-12-31T17:50:53.000Z",
      "contentLastModified": "31 Dec 2025 17:50 UTC",
      "serverLastModified": "Wed, 31 Dec 2025 17:50:53 GMT",
      "etag": "W/\"6955627d-1651a8\"",
      "size": 1462696,
      "changeReason": "content hash changed and timestamp newer and ETag changed",
      "expires": "4 days (update frequency)",
      "ageHours": "0.2",
      "isStale": false,
      "ageAnalysis": "Fresh: 0.2 hours old"
    }
  ],
  "staleFiles": []
}