{
  "updated": 2,
  "timestamp": "2026-05-22T01:36:46.222Z",
  "lists": [
    {
      "filename": "easylist.txt",
      "url": "https://easylist.to/easylist/easylist.txt",
      "hash": "34ced24b28589457430c3ba206eb9608a9cb41ef8f131c76480ce61c1c19ba63",
      "version": "202605220129",
      "lastModified": "2026-05-22T01:30:25.000Z",
      "contentLastModified": "22 May 2026 01:29 UTC",
      "serverLastModified": "Fri, 22 May 2026 01:30:25 GMT",
      "etag": "W/\"6a0fb1b1-228c75\"",
      "size": 2263263,
      "changeReason": "content hash changed and timestamp newer and ETag changed",
      "expires": "4 days (update frequency)",
      "ageHours": "0.1",
      "isStale": false,
      "ageAnalysis": "Fresh: 0.1 hours old"
    },
    {
      "filename": "easyprivacy.txt",
      "url": "https://easylist.to/easylist/easyprivacy.txt",
      "hash": "ee6825a5e400143f33cbbfd4f4fefb200ef0da1baca92ce3be6ada80bd3243cc",
      "version": "202605220113",
      "lastModified": "2026-05-22T01:13:46.000Z",
      "contentLastModified": "22 May 2026 01:13 UTC",
      "serverLastModified": "Fri, 22 May 2026 01:13:46 GMT",
      "etag": "W/\"6a0fadca-16afb6\"",
      "size": 1486774,
      "changeReason": "content hash changed and timestamp newer and ETag changed",
      "expires": "4 days (update frequency)",
      "ageHours": "0.4",
      "isStale": false,
      "ageAnalysis": "Fresh: 0.4 hours old"
    }
  ],
  "staleFiles": []
}