{
  "updated": 2,
  "timestamp": "2026-06-07T11:31:28.452Z",
  "lists": [
    {
      "filename": "easylist.txt",
      "url": "https://easylist.to/easylist/easylist.txt",
      "hash": "da373e2092474802ff929f2243cfecf44994bd682a08b2eb00316d16b44bc717",
      "version": "202606071114",
      "lastModified": "2026-06-07T11:14:41.000Z",
      "contentLastModified": "07 Jun 2026 11:14 UTC",
      "serverLastModified": "Sun, 07 Jun 2026 11:14:41 GMT",
      "etag": "W/\"6a2552a1-220eaf\"",
      "size": 2231065,
      "changeReason": "content hash changed and timestamp newer and ETag changed",
      "expires": "4 days (update frequency)",
      "ageHours": "0.3",
      "isStale": false,
      "ageAnalysis": "Fresh: 0.3 hours old"
    },
    {
      "filename": "easyprivacy.txt",
      "url": "https://easylist.to/easylist/easyprivacy.txt",
      "hash": "0a0fbe6723181ca17e629fea28f667a98c57f9d510ffb3aa2d61a1250c2e46ec",
      "version": "202606071114",
      "lastModified": "2026-06-07T11:14:41.000Z",
      "contentLastModified": "07 Jun 2026 11:14 UTC",
      "serverLastModified": "Sun, 07 Jun 2026 11:14:41 GMT",
      "etag": "W/\"6a2552a1-16a5bb\"",
      "size": 1484219,
      "changeReason": "content hash changed and timestamp newer and ETag changed",
      "expires": "4 days (update frequency)",
      "ageHours": "0.3",
      "isStale": false,
      "ageAnalysis": "Fresh: 0.3 hours old"
    }
  ],
  "staleFiles": []
}