{
  "updated": 2,
  "timestamp": "2026-05-01T04:30:32.093Z",
  "lists": [
    {
      "filename": "easylist.txt",
      "url": "https://easylist.to/easylist/easylist.txt",
      "hash": "9f978a2f5071bac3261cc0c6371a2c300e1763de15da46df5bafb456856d3c40",
      "version": "202605010412",
      "lastModified": "2026-05-01T04:12:48.000Z",
      "contentLastModified": "01 May 2026 04:12 UTC",
      "serverLastModified": "Fri, 01 May 2026 04:12:48 GMT",
      "etag": "W/\"69f42840-2309e3\"",
      "size": 2295373,
      "changeReason": "content hash changed and timestamp newer and ETag changed",
      "expires": "4 days (update frequency)",
      "ageHours": "0.3",
      "isStale": false,
      "ageAnalysis": "Fresh: 0.3 hours old"
    },
    {
      "filename": "easyprivacy.txt",
      "url": "https://easylist.to/easylist/easyprivacy.txt",
      "hash": "055f7e40c4feec208aa4fe20f29a61747454d78f5d0a0eb06a1fed35426bdbba",
      "version": "202605010412",
      "lastModified": "2026-05-01T04:12:48.000Z",
      "contentLastModified": "01 May 2026 04:12 UTC",
      "serverLastModified": "Fri, 01 May 2026 04:12:48 GMT",
      "etag": "W/\"69f42840-169d03\"",
      "size": 1481987,
      "changeReason": "content hash changed and timestamp newer and ETag changed",
      "expires": "4 days (update frequency)",
      "ageHours": "0.3",
      "isStale": false,
      "ageAnalysis": "Fresh: 0.3 hours old"
    }
  ],
  "staleFiles": []
}