{
  "updated": 2,
  "timestamp": "2026-03-01T03:56:39.798Z",
  "lists": [
    {
      "filename": "easylist.txt",
      "url": "https://easylist.to/easylist/easylist.txt",
      "hash": "edda8dc10a0272c0485e141d42a7dbc81865a9293b5039ee1745a8d0306ccd1d",
      "version": "202603010351",
      "lastModified": "2026-03-01T03:52:00.000Z",
      "contentLastModified": "01 Mar 2026 03:51 UTC",
      "serverLastModified": "Sun, 01 Mar 2026 03:52:00 GMT",
      "etag": "W/\"69a3b7e0-22ecf2\"",
      "size": 2288336,
      "changeReason": "content hash changed and timestamp newer and ETag changed",
      "expires": "4 days (update frequency)",
      "ageHours": "0.1",
      "isStale": false,
      "ageAnalysis": "Fresh: 0.1 hours old"
    },
    {
      "filename": "easyprivacy.txt",
      "url": "https://easylist.to/easylist/easyprivacy.txt",
      "hash": "13cb24237fc8c33f96d05b1ef640b317e708b5deb9f8e636dc04706cb80aa0f2",
      "version": "202603010345",
      "lastModified": "2026-03-01T03:46:02.000Z",
      "contentLastModified": "01 Mar 2026 03:45 UTC",
      "serverLastModified": "Sun, 01 Mar 2026 03:46:02 GMT",
      "etag": "W/\"69a3b67a-1678c6\"",
      "size": 1472710,
      "changeReason": "content hash changed and timestamp newer and ETag changed",
      "expires": "4 days (update frequency)",
      "ageHours": "0.2",
      "isStale": false,
      "ageAnalysis": "Fresh: 0.2 hours old"
    }
  ],
  "staleFiles": []
}