{
  "updated": 2,
  "timestamp": "2026-03-10T16:18:22.937Z",
  "lists": [
    {
      "filename": "easylist.txt",
      "url": "https://easylist.to/easylist/easylist.txt",
      "hash": "5b7946eb44a9881950fddc42506e1e6d4befcaaba43f9615597fdfd2500ea9ed",
      "version": "202603101608",
      "lastModified": "2026-03-10T16:14:21.000Z",
      "contentLastModified": "10 Mar 2026 16:08 UTC",
      "serverLastModified": "Tue, 10 Mar 2026 16:14:21 GMT",
      "etag": "W/\"69b0435d-229a3f\"",
      "size": 2267165,
      "changeReason": "content hash changed and timestamp newer and ETag changed",
      "expires": "4 days (update frequency)",
      "ageHours": "0.1",
      "isStale": false,
      "ageAnalysis": "Fresh: 0.2 hours old"
    },
    {
      "filename": "easyprivacy.txt",
      "url": "https://easylist.to/easylist/easyprivacy.txt",
      "hash": "49d263c3682a11769fc8244e129950a390ee5d83194ea5ce4830099ed1b81c61",
      "version": "202603101559",
      "lastModified": "2026-03-10T16:00:35.000Z",
      "contentLastModified": "10 Mar 2026 15:59 UTC",
      "serverLastModified": "Tue, 10 Mar 2026 16:00:35 GMT",
      "etag": "W/\"69b04023-167c4c\"",
      "size": 1473612,
      "changeReason": "content hash changed and timestamp newer and ETag changed",
      "expires": "4 days (update frequency)",
      "ageHours": "0.3",
      "isStale": false,
      "ageAnalysis": "Fresh: 0.3 hours old"
    }
  ],
  "staleFiles": []
}