{
  "updated": 2,
  "timestamp": "2026-02-11T02:58:47.368Z",
  "lists": [
    {
      "filename": "easylist.txt",
      "url": "https://easylist.to/easylist/easylist.txt",
      "hash": "bc8d32b7a4c24de00538672ec27b96eaffdb6759fa06c025e3b9fcc6e35388df",
      "version": "202602110248",
      "lastModified": "2026-02-11T02:49:28.000Z",
      "contentLastModified": "11 Feb 2026 02:48 UTC",
      "serverLastModified": "Wed, 11 Feb 2026 02:49:28 GMT",
      "etag": "W/\"698bee38-214957\"",
      "size": 2180917,
      "changeReason": "content hash changed and timestamp newer and ETag changed",
      "expires": "4 days (update frequency)",
      "ageHours": "0.2",
      "isStale": false,
      "ageAnalysis": "Fresh: 0.2 hours old"
    },
    {
      "filename": "easyprivacy.txt",
      "url": "https://easylist.to/easylist/easyprivacy.txt",
      "hash": "66449b44087e12e1d0a26868d3657d852f4998c638f82c9e20bad0cfb98e4a3d",
      "version": "202602110236",
      "lastModified": "2026-02-11T02:37:28.000Z",
      "contentLastModified": "11 Feb 2026 02:36 UTC",
      "serverLastModified": "Wed, 11 Feb 2026 02:37:28 GMT",
      "etag": "W/\"698beb68-16704c\"",
      "size": 1470540,
      "changeReason": "content hash changed and timestamp newer and ETag changed",
      "expires": "4 days (update frequency)",
      "ageHours": "0.4",
      "isStale": false,
      "ageAnalysis": "Fresh: 0.4 hours old"
    }
  ],
  "staleFiles": []
}