{
  "updated": 2,
  "timestamp": "2025-12-05T22:01:27.078Z",
  "lists": [
    {
      "filename": "easylist.txt",
      "url": "https://easylist.to/easylist/easylist.txt",
      "hash": "b86951ab63461659bf1acc9b0af8d99e06c2186c324460fb21a01af9e57288da",
      "version": "202512052150",
      "lastModified": "2025-12-05T21:50:40.000Z",
      "contentLastModified": "05 Dec 2025 21:50 UTC",
      "serverLastModified": "Fri, 05 Dec 2025 21:50:40 GMT",
      "etag": "W/\"693353b0-1e7e39\"",
      "size": 1997847,
      "changeReason": "content hash changed and timestamp newer and ETag changed",
      "expires": "4 days (update frequency)",
      "ageHours": "0.2",
      "isStale": false,
      "ageAnalysis": "Fresh: 0.2 hours old"
    },
    {
      "filename": "easyprivacy.txt",
      "url": "https://easylist.to/easylist/easyprivacy.txt",
      "hash": "c1034ffd419dde36cf44305e189401c2a9b645e7eee412270f1c1ef55d44c2e8",
      "version": "202512052150",
      "lastModified": "2025-12-05T21:50:40.000Z",
      "contentLastModified": "05 Dec 2025 21:50 UTC",
      "serverLastModified": "Fri, 05 Dec 2025 21:50:40 GMT",
      "etag": "W/\"693353b0-164248\"",
      "size": 1458760,
      "changeReason": "content hash changed and timestamp newer and ETag changed",
      "expires": "4 days (update frequency)",
      "ageHours": "0.2",
      "isStale": false,
      "ageAnalysis": "Fresh: 0.2 hours old"
    }
  ],
  "staleFiles": []
}