{
  "updated": 2,
  "timestamp": "2025-11-30T18:01:49.356Z",
  "lists": [
    {
      "filename": "easylist.txt",
      "url": "https://easylist.to/easylist/easylist.txt",
      "hash": "e2740b568d4226c1bdd82e977688b2bcc489fc3acf186027625eabf2791d8a9f",
      "version": "202511301744",
      "lastModified": "2025-11-30T17:45:04.000Z",
      "contentLastModified": "30 Nov 2025 17:44 UTC",
      "serverLastModified": "Sun, 30 Nov 2025 17:45:04 GMT",
      "etag": "W/\"692c82a0-1e212f\"",
      "size": 1974029,
      "changeReason": "content hash changed and timestamp newer and ETag changed",
      "expires": "4 days (update frequency)",
      "ageHours": "0.3",
      "isStale": false,
      "ageAnalysis": "Fresh: 0.3 hours old"
    },
    {
      "filename": "easyprivacy.txt",
      "url": "https://easylist.to/easylist/easyprivacy.txt",
      "hash": "0deff89982deda1f18981e0d5612d08025ff636b488ac5c0033cca1bce740423",
      "version": "202511301744",
      "lastModified": "2025-11-30T17:45:04.000Z",
      "contentLastModified": "30 Nov 2025 17:44 UTC",
      "serverLastModified": "Sun, 30 Nov 2025 17:45:04 GMT",
      "etag": "W/\"692c82a0-163ca3\"",
      "size": 1457315,
      "changeReason": "content hash changed and timestamp newer and ETag changed",
      "expires": "4 days (update frequency)",
      "ageHours": "0.3",
      "isStale": false,
      "ageAnalysis": "Fresh: 0.3 hours old"
    }
  ],
  "staleFiles": []
}