{
  "updated": 2,
  "timestamp": "2025-12-05T06:02:28.129Z",
  "lists": [
    {
      "filename": "easylist.txt",
      "url": "https://easylist.to/easylist/easylist.txt",
      "hash": "ee39f0078fa8e119e7843d8753a42b4ba89abc019fcfb508475b4aae4fa248ee",
      "version": "202512050547",
      "lastModified": "2025-12-05T05:47:46.000Z",
      "contentLastModified": "05 Dec 2025 05:47 UTC",
      "serverLastModified": "Fri, 05 Dec 2025 05:47:46 GMT",
      "etag": "W/\"69327202-1e6c73\"",
      "size": 1993297,
      "changeReason": "content hash changed and timestamp newer and ETag changed",
      "expires": "4 days (update frequency)",
      "ageHours": "0.2",
      "isStale": false,
      "ageAnalysis": "Fresh: 0.3 hours old"
    },
    {
      "filename": "easyprivacy.txt",
      "url": "https://easylist.to/easylist/easyprivacy.txt",
      "hash": "e701b7768a294739a6b705db974fbbe3ec04a3a9d1c3adf914ce938f765d7a44",
      "version": "202512050547",
      "lastModified": "2025-12-05T05:47:46.000Z",
      "contentLastModified": "05 Dec 2025 05:47 UTC",
      "serverLastModified": "Fri, 05 Dec 2025 05:47:46 GMT",
      "etag": "W/\"69327202-1641f1\"",
      "size": 1458673,
      "changeReason": "content hash changed and timestamp newer and ETag changed",
      "expires": "4 days (update frequency)",
      "ageHours": "0.2",
      "isStale": false,
      "ageAnalysis": "Fresh: 0.3 hours old"
    }
  ],
  "staleFiles": []
}